urnc/__init__.py
urnc/__main__.py
urnc/ci.py
urnc/config.py
urnc/convert.py
urnc/format.py
urnc/git.py
urnc/init.py
urnc/logger.py
urnc/main.py
urnc/pull.py
urnc/util.py
urnc/version.py
urnc/preprocessor/__init__.py
urnc/preprocessor/add_tags.py
urnc/preprocessor/check_outputs.py
urnc/preprocessor/clear_outputs.py
urnc/preprocessor/clear_tagged.py
urnc/preprocessor/executor.py
urnc/preprocessor/image.py
urnc/preprocessor/solutions.py
urnc/preprocessor/util.py
urnc-2.3.4.dist-info/licenses/LICENSE
urnc-2.3.4.dist-info/METADATA
urnc-2.3.4.dist-info/WHEEL
urnc-2.3.4.dist-info/entry_points.txt
urnc-2.3.4.dist-info/top_level.txt
urnc-2.3.4.dist-info/RECORD
